mixin_client/__init__.py
mixin_client/auth.py
mixin_client/client.py
mixin_client/config.py
mixin_client/http.py
mixin_client/models.py
mixin_client-0.4.5.dist-info/licenses/LICENSE
mixin_client-0.4.5.dist-info/METADATA
mixin_client-0.4.5.dist-info/WHEEL
mixin_client-0.4.5.dist-info/top_level.txt
mixin_client-0.4.5.dist-info/RECORD
