Metadata-Version: 2.4
Name: mixin-client
Version: 0.4.5
Summary: A Python client for Mixin Network
Author-email: Your Name <your.email@example.com>
License-Expression: MIT
Project-URL: Homepage, https://github.com/yourusername/mixin-client
Project-URL: Documentation, https://github.com/yourusername/mixin-client#readme
Project-URL: Repository, https://github.com/yourusername/mixin-client.git
Project-URL: Issues, https://github.com/yourusername/mixin-client/issues
Classifier: Programming Language :: Python :: 3
Classifier: Programming Language :: Python :: 3.9
Classifier: Programming Language :: Python :: 3.10
Classifier: Programming Language :: Python :: 3.11
Classifier: Programming Language :: Python :: 3.12
Classifier: Programming Language :: Python :: 3.13
Classifier: Operating System :: OS Independent
Requires-Python: >=3.9
License-File: LICENSE
Requires-Dist: requests>=2.25.1
Requires-Dist: websockets>=10.0
Requires-Dist: cryptography>=41.0.0
Requires-Dist: pydantic>=2.0.0
Requires-Dist: typing-extensions>=4.0.0
Dynamic: license-file
